ace/__init__.py
ace/agent.py
ace/config.py
ace/curator.py
ace/framework.py
ace/prompts.py
ace/reflector.py
ace/core/__init__.py
ace/core/generator.py
ace/middleware/__init__.py
ace/middleware/fallback.py
ace/playbook/__init__.py
ace/playbook/bullet.py
ace/playbook/manager.py
ace/utils/__init__.py
ace/utils/env.py
ace/utils/paths.py
ace/vectorstores/__init__.py
ace/vectorstores/base.py
ace/vectorstores/chromadb.py
ace/vectorstores/faiss.py
ace/vectorstores/qdrant.py
ace_context_engineering-0.1.4.dist-info/METADATA
ace_context_engineering-0.1.4.dist-info/WHEEL
ace_context_engineering-0.1.4.dist-info/licenses/LICENSE
ace_context_engineering-0.1.4.dist-info/RECORD
