Metadata-Version: 2.4
Name: ace-context-engineering
Version: 0.1.4
Summary: Agentic Context Engineering (ACE) - Evolving contexts for self-improving language models
Project-URL: Homepage, https://github.com/SuyodhanJ6/ace-context-engineering
Project-URL: Documentation, https://github.com/SuyodhanJ6/ace-context-engineering#readme
Project-URL: Repository, https://github.com/SuyodhanJ6/ace-context-engineering.git
Project-URL: Issues, https://github.com/SuyodhanJ6/ace-context-engineering/issues
Project-URL: Changelog, https://github.com/SuyodhanJ6/ace-context-engineering/blob/main/CHANGELOG.md
Author-email: Prashant Malge <prashantmalge101@gmail.com>
Maintainer-email: Prashant Malge <prashantmalge101@gmail.com>
License: MIT License
License-File: LICENSE
Keywords: agentic-ai,ai,context-engineering,curation,llm,playbook,reflection,self-improving
Classifier: Development Status :: 3 - Alpha
Classifier: Intended Audience :: Developers
Classifier: Intended Audience :: Science/Research
Classifier: License :: OSI Approved :: MIT License
Classifier: Operating System :: OS Independent
Classifier: Programming Language :: Python :: 3
Classifier: Programming Language :: Python :: 3.11
Classifier: Programming Language :: Python :: 3.12
Classifier: Topic :: Scientific/Engineering :: Artificial Intelligence
Classifier: Topic :: Software Development :: Libraries :: Python Modules
Requires-Python: >=3.11
Requires-Dist: faiss-cpu>=1.7.4
Requires-Dist: langchain-anthropic>=0.1.0
Requires-Dist: langchain-core>=0.1.0
Requires-Dist: langchain-openai>=0.1.0
Requires-Dist: langchain>=0.1.0
Requires-Dist: notebook>=7.4.7
Requires-Dist: numpy>=1.21.0
Requires-Dist: pydantic>=2.0.0
Requires-Dist: python-dotenv>=1.0.0
Requires-Dist: qdrant-client>=1.15.1
Provides-Extra: all
Requires-Dist: black>=23.0.0; extra == 'all'
Requires-Dist: chromadb>=0.4.0; extra == 'all'
Requires-Dist: flake8>=6.0.0; extra == 'all'
Requires-Dist: isort>=5.12.0; extra == 'all'
Requires-Dist: mkdocs-material>=9.0.0; extra == 'all'
Requires-Dist: mkdocs>=1.5.0; extra == 'all'
Requires-Dist: mkdocstrings>=0.22.0; extra == 'all'
Requires-Dist: mypy>=1.0.0; extra == 'all'
Requires-Dist: pre-commit>=3.0.0; extra == 'all'
Requires-Dist: pytest-asyncio>=0.21.0; extra == 'all'
Requires-Dist: pytest-cov>=4.0.0; extra == 'all'
Requires-Dist: pytest>=7.0.0; extra == 'all'
Provides-Extra: chromadb
Requires-Dist: chromadb>=0.4.0; extra == 'chromadb'
Provides-Extra: dev
Requires-Dist: black>=23.0.0; extra == 'dev'
Requires-Dist: flake8>=6.0.0; extra == 'dev'
Requires-Dist: isort>=5.12.0; extra == 'dev'
Requires-Dist: mypy>=1.0.0; extra == 'dev'
Requires-Dist: pre-commit>=3.0.0; extra == 'dev'
Requires-Dist: pytest-asyncio>=0.21.0; extra == 'dev'
Requires-Dist: pytest-cov>=4.0.0; extra == 'dev'
Requires-Dist: pytest>=7.0.0; extra == 'dev'
Provides-Extra: docs
Requires-Dist: mkdocs-material>=9.0.0; extra == 'docs'
Requires-Dist: mkdocs>=1.5.0; extra == 'docs'
Requires-Dist: mkdocstrings>=0.22.0; extra == 'docs'
